banglatts/__init__.py
banglatts/tts.py
BanglaTTS-0.0.3.dist-info/LICENSE
BanglaTTS-0.0.3.dist-info/METADATA
BanglaTTS-0.0.3.dist-info/WHEEL
BanglaTTS-0.0.3.dist-info/top_level.txt
BanglaTTS-0.0.3.dist-info/RECORD
